{"is_source_file": true, "format": "JavaScript (React JSX)", "description": "React component for the shopping cart page, managing cart items, displaying totals, and handling checkout process.", "external_files": ["../../store/useCartStore", "../../store/useAuthStore", "../../components/UI/Toast", "../../components/UI/EmptyState", "react", "react-router-dom"], "external_methods": ["useEffect", "useMemo", "useState", "useNavigate", "useCartStore", "useAuthStore", "Toast.info", "Link", "navigate"], "published": ["CartPage"], "classes": [], "methods": [{"name": "CartPage", "description": "Main React component rendering the cart page, handling cart interactions, totals calculation, and navigation."}], "calls": ["useEffect", "useMemo", "useState", "useNavigate", "useCartStore", "useAuthStore", "Toast.info", "navigate", "loadCartForUser", "removeCourse", "clearCart"], "search-terms": ["CartPage", "useCartStore", "useAuthStore", "React JSX cart component", "checkout process", "cart item management"], "state": 2, "file_id": 30, "knowledge_revision": 176, "git_revision": "6ac7b7eae5b8a3fdfb1219a40af08e13fb0ab712", "revision_history": [{"71": ""}, {"142": "9aec6f4fe6bd026c142be0ffa5c3cea22a35f287"}, {"176": "6ac7b7eae5b8a3fdfb1219a40af08e13fb0ab712"}], "ctags": [], "filename": "lms_frontend/src/pages/cart/CartPage.jsx", "format-version": 4, "code-base-name": "https://github.com/kavia-common/educonnect-learning-platform-268632-268641.git:kavia-main"}